LICENSE.md
MANIFEST.in
README.rst
pyproject.toml
requirements.core.txt
setup.py
core_composer_app/__init__.py
core_composer_app/admin.py
core_composer_app/apps.py
core_composer_app/menus.py
core_composer_app/models.py
core_composer_app/settings.py
core_composer_app/urls.py
core_composer_app.egg-info/PKG-INFO
core_composer_app.egg-info/SOURCES.txt
core_composer_app.egg-info/dependency_links.txt
core_composer_app.egg-info/requires.txt
core_composer_app.egg-info/top_level.txt
core_composer_app/components/__init__.py
core_composer_app/components/bucket/__init__.py
core_composer_app/components/bucket/api.py
core_composer_app/components/bucket/models.py
core_composer_app/components/type/__init__.py
core_composer_app/components/type/admin_site.py
core_composer_app/components/type/api.py
core_composer_app/components/type/models.py
core_composer_app/components/type_version_manager/__init__.py
core_composer_app/components/type_version_manager/admin_site.py
core_composer_app/components/type_version_manager/api.py
core_composer_app/components/type_version_manager/models.py
core_composer_app/migrations/0001_initial.py
core_composer_app/migrations/__init__.py
core_composer_app/permissions/__init__.py
core_composer_app/permissions/discover.py
core_composer_app/permissions/rights.py
core_composer_app/rest/__init__.py
core_composer_app/rest/urls.py
core_composer_app/rest/bucket/__init__.py
core_composer_app/rest/bucket/serializers.py
core_composer_app/rest/bucket/views.py
core_composer_app/rest/type_version_manager/__init__.py
core_composer_app/rest/type_version_manager/abstract_views.py
core_composer_app/rest/type_version_manager/serializers.py
core_composer_app/rest/type_version_manager/views.py
core_composer_app/static/core_composer_app/admin/js/bucket.js
core_composer_app/static/core_composer_app/admin/js/bucket.raw.js
core_composer_app/static/core_composer_app/admin/js/types/upload/dependencies.js
core_composer_app/static/core_composer_app/admin/js/types/upload/dependencies.raw.js
core_composer_app/static/core_composer_app/admin/js/types/upload/dependency_resolver.js
core_composer_app/static/core_composer_app/common/css/bucket.css
