Metadata-Version: 2.1
Name: core-composer-app
Version: 2.19.0
Summary: Template and type composer for the curator core project
Home-page: https://github.com/usnistgov/core_composer_app
Author: NIST IT Lab
Author-email: itl_inquiries@nist.gov
License-File: LICENSE.md
